alt-stubs/__init__.pyi
altv_stubs-1.0.3.dist-info/METADATA
altv_stubs-1.0.3.dist-info/WHEEL
altv_stubs-1.0.3.dist-info/top_level.txt
altv_stubs-1.0.3.dist-info/RECORD
