Metadata-Version: 2.1
Name: altv-stubs
Version: 1.0.3
Summary: Stubs for alt:V Python Module
Home-page: https://github.com/ZackaryH8/altv-python-stubs
Author: ZackaryH8 & Marvis
License: MIT
Keywords: mypy,altv
